[
    {
        "name":"Python",
        "logo":"Python.svg"
    },
    {
        "name":"Java",
        "logo":"Java.svg"
    },
    {
        "name":"C",
        "logo":"c.svg"
    },
    {
        "name":"C++",
        "logo":"cpp.svg"
    },
    {
        "name":"JavaScript",
        "logo":"javascript.svg"
    },
    {
        "name":"Dart",
        "logo":"dart.svg"
    },
    {
        "name":"-",
        "logo":"-"
    },
    {
        "name":"HTML",
        "logo":"html.svg"
    },
    {
        "name":"CSS",
        "logo":"css.svg"
    },
    {
        "name":"Bootstrap",
        "logo":"bootstrap.svg"
    },
    {
        "name":"jQuery",
        "logo":"jquery.svg"
    },
    {
        "name":"Flutter",
        "logo":"flutter.svg"
    },
    {
        "name":"-",
        "logo":"-"
    },
    {
        "name":"Flask",
        "logo":"Flask.svg"
    },
    {
        "name":"Django",
        "logo":"django.svg"
    },
    {
        "name":"-",
        "logo":"-"
    },
    {
        "name":"MySQL",
        "logo":"MySQL.svg"
    },
    {
        "name":"SQLite",
        "logo":"SQLite.svg"
    },
    {
        "name":"Redis",
        "logo":"Redis.svg"
    },
    {
        "name":"Firebase",
        "logo":"firebase.svg"
    },
    {
        "name":"MongoDB",
        "logo":"MongoDB.svg"
    },
    {
        "name":"-",
        "logo":"-"
    },
    {
        "name":"NumPy",
        "logo":"NumPy.svg"
    },
    {
        "name":"Pandas",
        "logo":"Pandas.svg"
    },
    {
        "name":"Matplotlib",
        "logo":"Matplotlib.svg"
    },
    {
        "name":"Seabron",
        "logo":"seaborn.svg"
    },
    {
        "name":"Scikit Learn",
        "logo":"scikit-learn.svg"
    },
    {
        "name":"-",
        "logo":"-"
    },
    {
        "name":"Power BI",
        "logo":"powerbi.svg"
    },
    {
        "name":"Apache Hadoop",
        "logo":"Apache Hadoop.svg"
    },
    {
        "name":"Git",
        "logo":"Git.svg"
    },
    {
        "name":"Selenium",
        "logo":"Selenium.svg"
    },
    {
        "name":"-",
        "logo":"-"
    },
    {
        "name":"Windows",
        "logo":"Windows 11.svg"
    },
    {
        "name":"Linux",
        "logo":"Linux.svg"
    },
    {
        "name":"Android",
        "logo":"Android.svg"
    }
]